slade/__init__.py
slade/analysis/__init__.py
slade/analysis/granger.py
slade/analysis/stationarity.py
slade/analysis/utils.py
slade/exceptions.py
slade/plot/correlation.py
slade/query/__init__.py
slade/query/kube/__init__.py
slade/query/kube/deployment.py
slade/query/locust/__init__.py
slade/query/locust/locust_querier.py
slade/query/prometheus/__init__.py
slade/query/prometheus/querier.py
slade/query/prometheus/query_builder.py
slade/query/trace/__init__.py
slade/query/trace/tracer.py
slade/utils.py
slade-1.5.0.dist-info/LICENSE
slade-1.5.0.dist-info/METADATA
slade-1.5.0.dist-info/WHEEL
slade-1.5.0.dist-info/RECORD
